tsdss/__init__.py
tsdss/surrogate.py
tsdss/tsds.py
utils/acf.cpython-39-darwin.so
utils/kurtosis.cpython-39-darwin.so
utils/lb.cpython-39-darwin.so
utils/skew.cpython-39-darwin.so
utils/trend.cpython-39-darwin.so
tsdss-0.2.0.dist-info/LICENSE
tsdss-0.2.0.dist-info/METADATA
tsdss-0.2.0.dist-info/WHEEL
tsdss-0.2.0.dist-info/top_level.txt
tsdss-0.2.0.dist-info/RECORD
