Metadata-Version: 2.1
Name: tsdss
Version: 0.2.0
Summary: Time Series Description
Home-page: https://github.com/wanghui5801/tsdss
Author: Hui Wang
Author-email: huiw1128@gmail.com
Classifier: Programming Language :: Python :: 3
Classifier: Programming Language :: C++
Classifier: License :: OSI Approved :: MIT License
Classifier: Operating System :: OS Independent
Requires-Python: >=3.7
License-File: LICENSE
Requires-Dist: numpy>=1.19.0
Requires-Dist: pandas>=1.0.0
Requires-Dist: statsmodels>=0.13.0
Requires-Dist: matplotlib>=3.0.0
Requires-Dist: scipy>=1.6.0
Requires-Dist: scikit-learn>=0.24.0
Provides-Extra: test
Requires-Dist: pytest>=6.0; extra == "test"
Requires-Dist: pytest-cov>=2.0; extra == "test"
Requires-Dist: numpy>=1.19.0; extra == "test"
Requires-Dist: pandas>=1.0.0; extra == "test"
Requires-Dist: scipy>=1.6.0; extra == "test"
Requires-Dist: statsmodels>=0.13.0; extra == "test"
Requires-Dist: matplotlib>=3.0.0; extra == "test"
Requires-Dist: scikit-learn>=0.24.0; extra == "test"
